pyzooms2s
